{
    "key": "group_58cc7eba82cdc",
    "title": "Resource Fields",
    "fields": [
        {
            "key": "field_586bc53317c55",
            "label": "Asset Summary",
            "name": "asset-summary",
            "type": "wysiwyg",
            "instructions": "Please include a short summary of this asset",
            "required": 1,
            "conditional_logic": 0,
            "wrapper": {
                "width": "",
                "class": "",
                "id": ""
            },
            "tabs": "all",
            "toolbar": "full",
            "media_upload": 0,
            "default_value": "",
            "delay": 0
        },
        {
            "key": "field_586bc55017c56",
            "label": "Asset Image",
            "name": "asset-image",
            "type": "image",
            "instructions": "Please include an image related to this asset",
            "required": 1,
            "conditional_logic": 0,
            "wrapper": {
                "width": "",
                "class": "",
                "id": ""
            },
            "return_format": "array",
            "preview_size": "thumbnail",
            "library": "all",
            "min_width": 0,
            "min_height": 0,
            "min_size": 0,
            "max_width": 0,
            "max_height": 0,
            "max_size": 0,
            "mime_types": ""
        },
        {
            "key": "field_586bc56b17c57",
            "label": "Asset Link",
            "name": "asset-link",
            "type": "text",
            "instructions": "Please provide a link to this asset",
            "required": 1,
            "conditional_logic": 0,
            "wrapper": {
                "width": "",
                "class": "",
                "id": ""
            },
            "default_value": "",
            "maxlength": "",
            "placeholder": "",
            "prepend": "",
            "append": "",
            "formatting": "none"
        },
        {
            "key": "field_5898893a26bce",
            "label": "Card Title",
            "name": "card-title",
            "type": "text",
            "instructions": "If you want the card to have a title different from the article title, input it here",
            "required": 0,
            "conditional_logic": 0,
            "wrapper": {
                "width": "",
                "class": "",
                "id": ""
            },
            "default_value": "",
            "maxlength": "",
            "placeholder": "",
            "prepend": "",
            "append": "",
            "formatting": "none"
        },
        {
            "key": "field_5898895426bcf",
            "label": "Hide Resource",
            "name": "hide_resource",
            "type": "true_false",
            "instructions": "",
            "required": 0,
            "conditional_logic": 0,
            "wrapper": {
                "width": "",
                "class": "",
                "id": ""
            },
            "default_value": 0,
            "message": "",
            "ui": 0,
            "ui_on_text": "",
            "ui_off_text": ""
        }
    ],
    "location": [
        [
            {
                "param": "post_type",
                "operator": "==",
                "value": "case_study"
            }
        ],
        [
            {
                "param": "post_type",
                "operator": "==",
                "value": "product_info"
            }
        ],
        [
            {
                "param": "post_type",
                "operator": "==",
                "value": "white_paper"
            }
        ],
        [
            {
                "param": "post_type",
                "operator": "==",
                "value": "video"
            }
        ]
    ],
    "menu_order": 0,
    "position": "acf_after_title",
    "style": "default",
    "label_placement": "top",
    "instruction_placement": "label",
    "hide_on_screen": [
        "the_content",
        "custom_fields",
        "discussion",
        "comments",
        "author",
        "categories",
        "tags"
    ],
    "active": 1,
    "description": "",
    "modified": 1514519610
}