{
    "key": "group_58cc7eba788e0",
    "title": "Resource",
    "fields": [
        {
            "key": "field_53a1e6e7ad781",
            "label": "Link",
            "name": "resource-link",
            "type": "text",
            "instructions": "",
            "required": 0,
            "conditional_logic": 0,
            "wrapper": {
                "width": "",
                "class": "",
                "id": ""
            },
            "default_value": "",
            "maxlength": "",
            "placeholder": "",
            "prepend": "",
            "append": "",
            "formatting": "none"
        },
        {
            "key": "field_53a1e96853c08",
            "label": "Subtitle",
            "name": "resource-subtitle",
            "type": "text",
            "instructions": "",
            "required": 0,
            "conditional_logic": 0,
            "wrapper": {
                "width": "",
                "class": "",
                "id": ""
            },
            "default_value": "",
            "maxlength": "",
            "placeholder": "",
            "prepend": "",
            "append": "",
            "formatting": "html"
        },
        {
            "key": "field_5429b5a8280a6",
            "label": "Search Engine Visibility",
            "name": "search_visibility_resource",
            "type": "select",
            "instructions": "Please select Yes if you want to hide this selected page from all search engines.",
            "required": 0,
            "conditional_logic": 0,
            "wrapper": {
                "width": "",
                "class": "",
                "id": ""
            },
            "multiple": 0,
            "allow_null": 0,
            "choices": {
                "Select": "Select",
                "Yes": "Yes",
                "No": "No"
            },
            "default_value": [],
            "ui": 0,
            "ajax": 0,
            "placeholder": "",
            "return_format": "value"
        }
    ],
    "location": [
        [
            {
                "param": "post_type",
                "operator": "==",
                "value": "post"
            }
        ]
    ],
    "menu_order": 0,
    "position": "acf_after_title",
    "style": "default",
    "label_placement": "top",
    "instruction_placement": "label",
    "hide_on_screen": [
        "permalink",
        "excerpt",
        "custom_fields",
        "discussion",
        "comments",
        "revisions",
        "slug",
        "author",
        "format",
        "categories",
        "tags",
        "send-trackbacks"
    ],
    "active": 1,
    "description": "",
    "modified": 1514519607
}